custom_attributes/__init__.py
custom_attributes/plugin.py
mkdocs_custom_tags_attributes-0.3.3.dist-info/LICENSE
mkdocs_custom_tags_attributes-0.3.3.dist-info/METADATA
mkdocs_custom_tags_attributes-0.3.3.dist-info/WHEEL
mkdocs_custom_tags_attributes-0.3.3.dist-info/entry_points.txt
mkdocs_custom_tags_attributes-0.3.3.dist-info/top_level.txt
mkdocs_custom_tags_attributes-0.3.3.dist-info/RECORD
