Metadata-Version: 2.1
Name: mkdocs-custom-tags-attributes
Version: 0.3.3
Summary: Adding custom attributes using hashtags.
Home-page: https://github.com/Mara-Li/mkdocs-custom-tags-attributes
Author: Mara-Li
Author-email: mara-li@outlook.fr
License: GPL-3
Keywords: mkdocs,custom attributes,markdown extension,markdown,md,attribute list,attr_list
Requires-Python: >=3.7
License-File: LICENSE
Requires-Dist: mkdocs
